matrix_mdp/__init__.py
matrix_mdp/envs/__init__.py
matrix_mdp/envs/matrix_mdp.py
matrix_mdp_gym-1.1.1.dist-info/LICENSE
matrix_mdp_gym-1.1.1.dist-info/METADATA
matrix_mdp_gym-1.1.1.dist-info/WHEEL
matrix_mdp_gym-1.1.1.dist-info/top_level.txt
matrix_mdp_gym-1.1.1.dist-info/RECORD
