Metadata-Version: 2.1
Name: matrix-mdp-gym
Version: 1.1.1
Summary: An OpenAI gym / Gymnasium environment to seamlessly create discrete MDPs from matrices.
Home-page: https://github.com/Paul-543NA/matrix-mdp-gym
Author: Paul Festor
Author-email: paul.festor@gmail.com
License: MIT License
Keywords: Reinforcement-Learning Reinforcement-Learning-Environment Gym-Environment Markov-Decision-Processes Gym OpenAI-Gym Gymnasium
Classifier: Programming Language :: Python :: 3
Classifier: Programming Language :: Python :: 3 :: Only
Classifier: Programming Language :: Python :: 3.6
Classifier: Programming Language :: Python :: 3.7
Classifier: Programming Language :: Python :: 3.8
Classifier: Programming Language :: Python :: 3.9
Classifier: License :: OSI Approved :: MIT License
Classifier: Operating System :: OS Independent
Classifier: Intended Audience :: Developers
Classifier: Intended Audience :: Education
Classifier: Intended Audience :: Science/Research
Classifier: Topic :: Scientific/Engineering
Classifier: Topic :: Scientific/Engineering :: Mathematics
Classifier: Topic :: Scientific/Engineering :: Artificial Intelligence
Classifier: Topic :: Software Development
Classifier: Topic :: Software Development :: Libraries
Classifier: Topic :: Software Development :: Libraries :: Python Modules
Requires-Python: >=3.6
License-File: LICENSE
Requires-Dist: gymnasium (>=0.26.2)
Requires-Dist: numpy (>=1.19.5)
